purviewautomation/__init__.py
purviewautomation/auth.py
purviewautomation/collections.py
purviewautomation-0.1.7.dist-info/METADATA
purviewautomation-0.1.7.dist-info/WHEEL
purviewautomation-0.1.7.dist-info/licenses/LICENSE
purviewautomation-0.1.7.dist-info/RECORD
