Metadata-Version: 2.1
Name: purviewautomation
Version: 0.1.7
Summary: Purview Automation is a Python wrapper library built on top of Purview REST APIs that's designed to be simple to use and make scaling and automating Purview easier.
Project-URL: Homepage, https://github.com/Ludwinic1/purviewautomation
Project-URL: Documentation, https://purviewautomation.netlify.app
Author-email: Nick Ludwig <nick.ludwig223@gmail.com>
License-File: LICENSE
Classifier: License :: OSI Approved :: MIT License
Classifier: Operating System :: OS Independent
Classifier: Programming Language :: Python
Classifier: Programming Language :: Python :: 3
Classifier: Programming Language :: Python :: 3 :: Only
Classifier: Programming Language :: Python :: 3.8
Classifier: Programming Language :: Python :: 3.9
Classifier: Programming Language :: Python :: 3.10
Classifier: Programming Language :: Python :: 3.11
Classifier: Topic :: Software Development
Classifier: Topic :: Software Development :: Libraries
Classifier: Topic :: Software Development :: Libraries :: Python Modules
Requires-Python: >=3.8
Requires-Dist: requests>=2.28.1
Provides-Extra: dev
Requires-Dist: pre-commit==2.20.0; extra == 'dev'
Provides-Extra: doc
Requires-Dist: mkdocs-material>=8.1.4; extra == 'doc'
Requires-Dist: mkdocs>=1.1.2; extra == 'doc'
Requires-Dist: mkdocstrings-python==0.7.1; extra == 'doc'
Requires-Dist: mkdocstrings==0.19.0; extra == 'doc'
Requires-Dist: termynal==0.2.0; extra == 'doc'
Provides-Extra: test
Requires-Dist: azure-identity==1.12.0; extra == 'test'
Requires-Dist: black==22.10.0; extra == 'test'
Requires-Dist: coverage==6.5.0; extra == 'test'
Requires-Dist: isort>=5.10.1; extra == 'test'
Requires-Dist: pytest==7.2.0; extra == 'test'
